aleph_utils/__init__.py
aleph_utils/make_ids.py
aleph_utils/nombre_en_francais.py
aleph_utils/store_utils.py
aleph_utils-0.0.1.dist-info/LICENSE
aleph_utils-0.0.1.dist-info/METADATA
aleph_utils-0.0.1.dist-info/WHEEL
aleph_utils-0.0.1.dist-info/top_level.txt
aleph_utils-0.0.1.dist-info/RECORD
