Metadata-Version: 2.1
Name: aleph-utils
Version: 0.0.1
Summary: Des utilitaires pour Aleph
Home-page: https://github.com/manonromain/aleph_utils
Author: Manon Romain
Author-email: manonr96@gmail.com
License: UNKNOWN
Project-URL: Bug Tracker, https://github.com/manonromain/aleph_utils/issues
Platform: UNKNOWN
Classifier: Programming Language :: Python :: 3
Classifier: License :: OSI Approved :: MIT License
Classifier: Operating System :: OS Independent
Requires-Python: >=3.8
License-File: LICENSE
